mujson/__init__.py
mujson-1.4.dist-info/DESCRIPTION.rst
mujson-1.4.dist-info/LICENSE.txt
mujson-1.4.dist-info/METADATA
mujson-1.4.dist-info/RECORD
mujson-1.4.dist-info/WHEEL
mujson-1.4.dist-info/metadata.json
mujson-1.4.dist-info/top_level.txt
